add_umn/__init__.py
add_umn/addition_umn.py
addition_umn-0.0.1.dist-info/LICENSE
addition_umn-0.0.1.dist-info/METADATA
addition_umn-0.0.1.dist-info/WHEEL
addition_umn-0.0.1.dist-info/top_level.txt
addition_umn-0.0.1.dist-info/RECORD
