Metadata-Version: 2.1
Name: addition_umn
Version: 0.0.1
Summary: This is for testing the python package umn
Author: Umeshn7Codes
Requires-Python: >=3.6
License-File: LICENSE
